selenium_loader/__init__.py
selenium_loader/action_executor.py
selenium_loader/browser.py
selenium_loader/custom_web_driver_handler.py
selenium_loader/utils/__init__.py
selenium_loader/utils/browser_type.py
selenium_loader/utils/config_validator.py
selenium_loader-0.2.0.dist-info/LICENSE
selenium_loader-0.2.0.dist-info/WHEEL
selenium_loader-0.2.0.dist-info/METADATA
selenium_loader-0.2.0.dist-info/RECORD
