Metadata-Version: 2.1
Name: selenium_loader
Version: 0.2.0
Summary: Configuration loader and action executor for Selenium
Author-email: kevocde <kevocde@gmail.com>
Requires-Python: >=3.6
Classifier: License :: OSI Approved :: Apache Software License
Requires-Dist: selenium>=4.8.0
Requires-Dist: typer>=0.7.0
Requires-Dist: mergedeep>=1.3.4
Project-URL: Home, https://kevocde.github.io/selenium-loader
Project-URL: Source, https://github.com/kevocde/selenium-loader.git
